[
    {
		"name": "2048",
		"show": "https://codepen.io/jacktown/full/zdWvZL/",
        "github": "https://github.com/jacktown11/2048",
        "cover": "2048.gif"
    },
    {
        "name": "calculator",
        "show": "https://codepen.io/jacktown/full/ZJBdPq/",
        "github": "https://github.com/jacktown11/fcc/tree/master/calculator",
        "cover": "calculator.gif"
    },
    {
        "name": "simon game",
        "show": "https://codepen.io/jacktown/full/gxvaMr/",
        "github": "https://github.com/jacktown11/fcc/tree/master/simon",
        "cover": "simon.gif"
    },
    {
        "name": "tictactoe game",
        "show": "https://codepen.io/jacktown/full/PKjVpj/",
        "github": "",
        "cover": "tictactoe.gif"
    },
    {
        "name": "twitch api",
        "show": "https://codepen.io/jacktown/full/KvMLxv/",
        "github": "https://github.com/jacktown11/fcc/tree/master/usingTwitchTv0",
        "cover": "twitch.gif"
    },
    {
        "name": "local weather",
        "show": "https://codepen.io/jacktown/full/EvaBKv/",
        "github": "https://github.com/jacktown11/fcc/tree/master/getWeather0",
        "cover": "weather.gif"
    },
    {
        "name": "wikipedia viewer",
        "show": "https://codepen.io/jacktown/full/RZWLNR/",
        "github": "https://github.com/jacktown11/fcc/tree/master/wikipediaViewer0",
        "cover": "wikipedia.gif"
    },
    {
        "name": "pomodoro",
        "show": "https://codepen.io/jacktown/full/Ljjxby/",
        "github": "https://github.com/jacktown11/fcc/tree/master/pomodoro",
        "cover": "pomodoro.gif"
    },
    {
		"name": "barrage",
		"show": "https://codepen.io/jacktown/full/awjjGz/",
        "github": "https://github.com/jacktown11/fcc/tree/master/barrage",
        "cover": "barriage.jpg"
    },
    {
		"name": "portfolio",
		"show": "https://codepen.io/jacktown/full/eRrYyJ/",
        "github": "https://github.com/jacktown11/fcc/tree/master/Build_a_Personal_Portfolio_Webpage0",
        "cover": "portfolio.jpg"
    },
    {
		"name": "random quote",
		"show": "https://codepen.io/jacktown/full/rzaBMO/",
        "github": "https://github.com/jacktown11/fcc/tree/master/RandomQuoteMachine0",
        "cover": "quote.jpg"
    },
    {
		"name": "tribute page",
		"show": "https://codepen.io/jacktown/full/eRMamL/",
        "github": "https://github.com/jacktown11/fcc/tree/master/Build_a_Tribute_Page0",
        "cover": "tribute.jpg"
    }
   
]